keble_async/__init__.py
keble_async/worker.py
keble_async-0.0.0.dist-info/METADATA
keble_async-0.0.0.dist-info/WHEEL
keble_async-0.0.0.dist-info/RECORD
