Metadata-Version: 2.1
Name: keble-async
Version: 0.0.0
Summary: 
Author: AndrewChan
Author-email: 1085718846@qq.com
Requires-Python: >=3.10,<4.0
Classifier: Programming Language :: Python :: 3
Classifier: Programming Language :: Python :: 3.10
Classifier: Programming Language :: Python :: 3.11
Classifier: Programming Language :: Python :: 3.12
Requires-Dist: aiofiles (>=23.2.1,<24.0.0)
Requires-Dist: aiohttp (>=3.9.5,<4.0.0)
Requires-Dist: asyncio (>=3.4.3,<4.0.0)
Requires-Dist: httpx (>=0.27.0,<0.28.0)
Requires-Dist: redis (>=5.0.3,<6.0.0)
